dotbot_utils/__init__.py
dotbot_utils/hdlc.py
dotbot_utils/protocol.py
dotbot_utils/serial_interface.py
dotbot_utils/tests/__init__.py
dotbot_utils/tests/test_hdlc_handler.py
dotbot_utils/tests/test_protocol.py
dotbot_utils/tests/test_serial_interface.py
pydotbot_utils-0.3.0.dist-info/METADATA
pydotbot_utils-0.3.0.dist-info/WHEEL
pydotbot_utils-0.3.0.dist-info/licenses/LICENSE.txt
pydotbot_utils-0.3.0.dist-info/RECORD
