Metadata-Version: 2.4
Name: pydotbot-utils
Version: 0.3.0
Summary: Utility modules for the DotBot Python softwares.
Project-URL: Homepage, https://github.com/DotBots/PyDotBot-utils
Project-URL: Bug Tracker, https://github.com/DotBots/PyDotBot-utils/issues
Author-email: Alexandre Abadie <alexandre.abadie@inria.fr>
License: BSD
License-File: LICENSE.txt
Classifier: License :: OSI Approved :: BSD License
Classifier: Operating System :: MacOS
Classifier: Operating System :: Microsoft :: Windows
Classifier: Operating System :: POSIX :: Linux
Classifier: Programming Language :: Python :: 3
Requires-Python: >=3.7
Requires-Dist: pyserial>=3.5
